fastapi_startkit_database/__init__.py
fastapi_startkit_database/providers/DatabaseProvider.py
fastapi_startkit_database/providers/__init__.py
fastapi_startkit_database-0.1.0.dist-info/METADATA
fastapi_startkit_database-0.1.0.dist-info/WHEEL
fastapi_startkit_database-0.1.0.dist-info/RECORD
