Metadata-Version: 2.4
Name: fastapi-startkit-database
Version: 0.1.0
Summary: Database module for FastAPI StartKit
Author: Bedram Tamang
Author-email: tmgbedu@gmail.com
Requires-Python: >=3.12,<4.0
Classifier: Programming Language :: Python :: 3
Classifier: Programming Language :: Python :: 3.12
Classifier: Programming Language :: Python :: 3.13
Classifier: Programming Language :: Python :: 3.14
Requires-Dist: masonite-orm (>=3.0.0,<4.0.0)
